gaussianutility/__init__.py
gaussianutility/com2vasp.py
gaussianutility/com2xyz.py
gaussianutility/freezeLayer.py
gaussianutility/gibbsTemp.py
gaussianutility/out2com.py
gaussianutility/printE.py
gaussianutility/sortInput.py
gaussianutility/spectrum.py
gaussianutility/utilities.py
gaussianutility/vasp2com.py
gaussianutility/xyz2com.py
gaussianutility-0.1.6.dist-info/LICENSE
gaussianutility-0.1.6.dist-info/METADATA
gaussianutility-0.1.6.dist-info/WHEEL
gaussianutility-0.1.6.dist-info/entry_points.txt
gaussianutility-0.1.6.dist-info/top_level.txt
gaussianutility-0.1.6.dist-info/RECORD
