Metadata-Version: 2.1
Name: gaussianutility
Version: 0.1.6
Summary: Useful utilities to use Gaussian09/16 software
Home-page: https://github.com/Sungil-Hong/gaussianutility
Author: Sungil Hong
Author-email: Sungil Hong <s.hong@pitt.edu>
Classifier: Programming Language :: Python :: 3
Classifier: License :: OSI Approved :: MIT License
Classifier: Operating System :: OS Independent
Requires-Python: >=3.6
License-File: LICENSE
Requires-Dist: numpy>=1.17.2
Requires-Dist: pandas>=1.1.0
Requires-Dist: periodictable>=1.6.1
Requires-Dist: argparse>=1.1
Requires-Dist: matplotlib>=3.5.1
Requires-Dist: mendeleev>=0.9.0
